plate_recognize_py/__init__.py
plate_recognize_py/utils.py
PlateRecognizePy-0.2.2.dist-info/LICENSE
PlateRecognizePy-0.2.2.dist-info/METADATA
PlateRecognizePy-0.2.2.dist-info/WHEEL
PlateRecognizePy-0.2.2.dist-info/top_level.txt
PlateRecognizePy-0.2.2.dist-info/RECORD
