Metadata-Version: 2.1
Name: PlateRecognizePy
Version: 0.2.2
Summary: A Python library for license plate detection and recognition
Home-page: https://github.com/techbyvj/PlateRecognizePy
Author: VJ
Author-email: 
Classifier: Development Status :: 3 - Alpha
Classifier: Intended Audience :: Developers
Classifier: License :: OSI Approved :: MIT License
Classifier: Operating System :: OS Independent
Classifier: Programming Language :: Python :: 3
Classifier: Programming Language :: Python :: 3.7
Classifier: Programming Language :: Python :: 3.8
Classifier: Programming Language :: Python :: 3.9
Requires-Python: >=3.7
License-File: LICENSE
Requires-Dist: pytesseract
Requires-Dist: easyocr
Requires-Dist: opencv-python
Requires-Dist: numpy
Requires-Dist: ultralytics
